qpageview/__init__.py
qpageview/backgroundjob.py
qpageview/cache.py
qpageview/constants.py
qpageview/cupsprinter.py
qpageview/diff.py
qpageview/document.py
qpageview/export.py
qpageview/highlight.py
qpageview/image.py
qpageview/imageview.py
qpageview/layout.py
qpageview/link.py
qpageview/locking.py
qpageview/magnifier.py
qpageview/multipage.py
qpageview/page.py
qpageview/pdf.py
qpageview/pkginfo.py
qpageview/printing.py
qpageview/rectangles.py
qpageview/render.py
qpageview/rubberband.py
qpageview/scrollarea.py
qpageview/selector.py
qpageview/shadow.py
qpageview/sidebarview.py
qpageview/svg.py
qpageview/util.py
qpageview/view.py
qpageview/viewactions.py
qpageview/widgetoverlay.py
qpageview-1.0.3.dist-info/METADATA
qpageview-1.0.3.dist-info/WHEEL
qpageview-1.0.3.dist-info/licenses/LICENSE
qpageview-1.0.3.dist-info/RECORD
