Metadata-Version: 2.4
Name: qpageview
Version: 1.0.3
Summary: Widget to display page-based documents for Qt6/PyQt6
Project-URL: Homepage, https://github.com/frescobaldi/qpageview
Project-URL: Documentation, https://qpageview.org
Project-URL: Issue tracker, https://github.com/frescobaldi/qpageview/issues
Maintainer-email: Wilbert Berendsen <info@frescobaldi.org>
License: GPL v3
License-File: LICENSE
Classifier: Development Status :: 5 - Production/Stable
Classifier: Intended Audience :: Developers
Classifier: License :: OSI Approved :: GNU General Public License v3 or later (GPLv3+)
Classifier: Operating System :: MacOS :: MacOS X
Classifier: Operating System :: Microsoft :: Windows
Classifier: Operating System :: POSIX
Classifier: Programming Language :: Python :: 3.7
Classifier: Topic :: Multimedia :: Graphics
Requires-Python: >=3.7
Requires-Dist: pyqt6>=6.6
Provides-Extra: cups
Requires-Dist: pycups; extra == 'cups'
